oneforall/__init__.py
oneforall/bundler.py
oneforall/cli.py
oneforall/defaults.py
oneforall/unbundler.py
oneforall-0.1.1.dist-info/licenses/LICENSE
oneforall-0.1.1.dist-info/METADATA
oneforall-0.1.1.dist-info/WHEEL
oneforall-0.1.1.dist-info/entry_points.txt
oneforall-0.1.1.dist-info/top_level.txt
oneforall-0.1.1.dist-info/RECORD
