Metadata-Version: 2.4
Name: oneforall
Version: 0.1.1
Summary: A tool to pack and unpack project files into a single file for easy sharing and LLM interaction.
Author-email: Bijaya Acharya <contact@achbj.com>
License: MIT License
Project-URL: Homepage, https://github.com/yourusername/oneforall
Project-URL: Issues, https://github.com/yourusername/oneforall/issues
Classifier: Programming Language :: Python :: 3
Classifier: Programming Language :: Python :: 3.7
Classifier: Programming Language :: Python :: 3.8
Classifier: Programming Language :: Python :: 3.9
Classifier: Programming Language :: Python :: 3.10
Classifier: Programming Language :: Python :: 3.11
Classifier: Programming Language :: Python :: 3.12
Classifier: License :: OSI Approved :: MIT License
Classifier: Operating System :: OS Independent
Classifier: Topic :: Software Development :: Build Tools
Classifier: Topic :: Utilities
Classifier: Environment :: Console
Classifier: Intended Audience :: Developers
Requires-Python: >=3.7
License-File: LICENSE
Requires-Dist: pathspec>=0.9.0
Dynamic: license-file
